.gitignore
CHANGES.rst
MANIFEST.in
README.rst
README.txt
setup.py
kss/__init__.py
kss.plugin.yuidnd.egg-info/PKG-INFO
kss.plugin.yuidnd.egg-info/SOURCES.txt
kss.plugin.yuidnd.egg-info/dependency_links.txt
kss.plugin.yuidnd.egg-info/entry_points.txt
kss.plugin.yuidnd.egg-info/namespace_packages.txt
kss.plugin.yuidnd.egg-info/not-zip-safe
kss.plugin.yuidnd.egg-info/requires.txt
kss.plugin.yuidnd.egg-info/top_level.txt
kss/plugin/__init__.py
kss/plugin/yuidnd/__init__.py
kss/plugin/yuidnd/configure.zcml
kss/plugin/yuidnd/kss.plugin.yuidnd-configure.zcml
kss/plugin/yuidnd/3rd_party/animation-min.js
kss/plugin/yuidnd/3rd_party/animation.js
kss/plugin/yuidnd/3rd_party/dom-min.js
kss/plugin/yuidnd/3rd_party/dom.js
kss/plugin/yuidnd/3rd_party/dragdrop-min.js
kss/plugin/yuidnd/3rd_party/dragdrop.js
kss/plugin/yuidnd/3rd_party/event-min.js
kss/plugin/yuidnd/3rd_party/event.js
kss/plugin/yuidnd/3rd_party/yahoo-min.js
kss/plugin/yuidnd/3rd_party/yahoo.js
kss/plugin/yuidnd/demo/__init__.py
kss/plugin/yuidnd/demo/configure.zcml
kss/plugin/yuidnd/demo/kss_yuidnd_orderable_demo.css
kss/plugin/yuidnd/demo/kss_yuidnd_orderable_demo.kss
kss/plugin/yuidnd/demo/kss_yuidnd_orderable_demo.pt
kss/plugin/yuidnd/demo/zopeconfig.py
kss/plugin/yuidnd/javascript/kss_dragdrop.js