Metadata-Version: 1.0
Name: kss.plugin.yuidnd
Version: 1.1
Summary: A plugin for KSS that provides drag-and-drop based on yahoo.ui
Home-page: https://plone.org/products/extreme-management-tool/
Author: Jean-Paul Ladage
Author-email: j.ladage@zestsoftware.nl
License: GPL
Keywords: kss plugin drag-and-drop
Platform: UNKNOWN
Classifier: Framework :: Plone
Classifier: Framework :: Zope2
Classifier: Framework :: Zope3
Classifier: Programming Language :: Python
Classifier: Topic :: Software Development :: Libraries :: Python Modules
